README.md
setup.cfg
setup.py
probabilty_dist_2types/Binomialdistribution.py
probabilty_dist_2types/Gaussiandistribution.py
probabilty_dist_2types/Generaldistribution.py
probabilty_dist_2types/__init__.py
probabilty_dist_2types.egg-info/PKG-INFO
probabilty_dist_2types.egg-info/SOURCES.txt
probabilty_dist_2types.egg-info/dependency_links.txt
probabilty_dist_2types.egg-info/not-zip-safe
probabilty_dist_2types.egg-info/top_level.txt