Metadata-Version: 1.0
Name: probabilty-dist-2types
Version: 0.1
Summary: Gaussian distributions
Home-page: UNKNOWN
Author: UNKNOWN
Author-email: UNKNOWN
License: UNKNOWN
Platform: UNKNOWN
